topsis_analysis/__init__.py
topsis_analysis/topsispackage.py
TOPSIS_Karanbir_101803235-0.1.dist-info/METADATA
TOPSIS_Karanbir_101803235-0.1.dist-info/WHEEL
TOPSIS_Karanbir_101803235-0.1.dist-info/top_level.txt
TOPSIS_Karanbir_101803235-0.1.dist-info/RECORD
