Metadata-Version: 2.1
Name: TOPSIS-Karanbir-101803235
Version: 0.1
Summary: topsis marking for dataset to be ranked according to topsis analysis
Home-page: UNKNOWN
Author: Karanbir singh
Author-email: karanchopra21061999@gmail.com
License: MIT
Keywords: TOPSIS
Platform: UNKNOWN
Classifier: Development Status :: 3 - Alpha
Classifier: Intended Audience :: Developers
Classifier: Topic :: Software Development :: Build Tools
Classifier: License :: OSI Approved :: MIT License
Classifier: Programming Language :: Python :: 3
Classifier: Programming Language :: Python :: 3.4
Classifier: Programming Language :: Python :: 3.5
Classifier: Programming Language :: Python :: 3.6
Requires-Dist: pandas
